missing_python/missing_values.py
Missing_values_101883058-1.0.2.dist-info/LICENSE.txt
Missing_values_101883058-1.0.2.dist-info/METADATA
Missing_values_101883058-1.0.2.dist-info/WHEEL
Missing_values_101883058-1.0.2.dist-info/entry_points.txt
Missing_values_101883058-1.0.2.dist-info/top_level.txt
Missing_values_101883058-1.0.2.dist-info/RECORD
