Metadata-Version: 2.1
Name: Missing-values-101883058
Version: 1.0.2
Summary: Replacing missing values in the dataset with the mean of that particular column using SimpleImputer class.
Home-page: UNKNOWN
Author: Pritpal Singh Pruthi
Author-email: psp.ps001@gmail.com
License: MIT
Platform: UNKNOWN
Classifier: License :: OSI Approved :: MIT License
Classifier: Programming Language :: Python :: 3
Classifier: Programming Language :: Python :: 3.4
Classifier: Programming Language :: Python :: 3.5
Classifier: Programming Language :: Python :: 3.6
Classifier: Programming Language :: Python :: 3.7
Requires-Dist: numpy
Requires-Dist: pandas
